MANIFEST.in
README.md
requirements.txt
setup.py
kowalsky/__init__.py
kowalsky/colab.py
kowalsky/df.py
kowalsky/feature.py
kowalsky/kaggle.py
kowalsky/metrics.py
kowalsky/model.py
kowalsky/nn.py
kowalsky/tune.py
kowalsky.egg-info/PKG-INFO
kowalsky.egg-info/SOURCES.txt
kowalsky.egg-info/dependency_links.txt
kowalsky.egg-info/requires.txt
kowalsky.egg-info/top_level.txt
kowalsky/logs/__init__.py
kowalsky/logs/loggers.py
kowalsky/logs/utils.py