Metadata-Version: 2.1
Name: kowalsky
Version: 0.0.44
Summary: A small package for all useful ML things
Home-page: https://github.com/NikitaGordia/Kowalsky
Author: Nikita Gordia
Author-email: nikita.gordia@gmail.com
License: UNKNOWN
Platform: UNKNOWN
Classifier: Programming Language :: Python :: 3
Classifier: License :: OSI Approved :: MIT License
Classifier: Operating System :: OS Independent
Requires-Python: >=3.6
